dupco/__init__.py
dupco/aes.py
dupco/client.py
dupco/common.py
dupco-0.0.6.dist-info/LICENSE
dupco-0.0.6.dist-info/METADATA
dupco-0.0.6.dist-info/WHEEL
dupco-0.0.6.dist-info/top_level.txt
dupco-0.0.6.dist-info/RECORD
