Metadata-Version: 2.1
Name: dupco
Version: 0.0.6
Summary: A simple way to call DigitalUnion service
Home-page: https://github.com/DigitalUnion/du-pco-py-sdk
Author: gaojian
Author-email: gaojian@shuzilm.cn
Classifier: Programming Language :: Python :: 3
Classifier: License :: OSI Approved :: MIT License
Classifier: Operating System :: OS Independent
Requires-Python: >=3.6
License-File: LICENSE
Requires-Dist: pycryptodome (==3.15.0)
Requires-Dist: requests (==2.28.1)
